ddr_cantera/__init__.py
ddr_cantera/fuel_data.py
ddr_cantera/pipe.py
ddr_cantera/shared.py
ddr_cantera/utils.py
ddr_cantera/version.py
ddr_cantera-0.0.3.dist-info/METADATA
ddr_cantera-0.0.3.dist-info/WHEEL
ddr_cantera-0.0.3.dist-info/top_level.txt
ddr_cantera-0.0.3.dist-info/RECORD
