Metadata-Version: 2.1
Name: ddr-cantera
Version: 0.0.3
Summary: Package to calculate air properties using cantera
Home-page: https://github.com/ddrathod121294/ddr_davis_data
Author: Darshan Rathod
Author-email: darshan.rathod1994@gmail.com
Keywords: ddr,ddr_cantera
Classifier: Development Status :: 2 - Pre-Alpha
Classifier: Intended Audience :: Education
Classifier: Intended Audience :: Science/Research
Classifier: Natural Language :: English
Classifier: Topic :: Education
Classifier: Topic :: Scientific/Engineering
Classifier: Topic :: Scientific/Engineering :: Physics
Classifier: Programming Language :: Python :: 3.6
Requires-Python: >=3.6, <4
Requires-Dist: numpy
Requires-Dist: cantera
